MANIFEST.in
README.rst
setup.py
curator/__init__.py
curator/cle.py
curator/cli.py
curator/console.py
curator/driver.py
librarian_curator.egg-info/PKG-INFO
librarian_curator.egg-info/SOURCES.txt
librarian_curator.egg-info/dependency_links.txt
librarian_curator.egg-info/entry_points.txt
librarian_curator.egg-info/requires.txt
librarian_curator.egg-info/top_level.txt