Metadata-Version: 1.1
Name: librarian-curator
Version: 0.1.0
Summary: None
Home-page: nekroze.eturnilnetwork.com
Author: Taylor "Nekroze" Lawson
Author-email: nekroze@eturnilnetwork.com
License: MIT
Platform: any
Classifier: Development Status :: 4 - Beta
Classifier: Environment :: Console
Classifier: Intended Audience :: Developers
Classifier: License :: OSI Approved :: MIT License
Classifier: Operating System :: OS Independent
Classifier: Topic :: Games/Entertainment
Classifier: Topic :: Utilities
